pyconcr/__init__.py
pyconcr/_version.py
pyconcr/pyconcr.py
pyconcr/cli/.gitkeep
pyconcr/cli/.pyconcr.py.~undo-tree~.zst
pyconcr/cli/pyconcr.py
pyconcr/data/.gitkeep
pyconcr/data/BrysbaertEtAl2014a/.__init__.py.~undo-tree~.zst
pyconcr/data/BrysbaertEtAl2014a/.concr.json.~undo-tree~.zst
pyconcr/data/BrysbaertEtAl2014a/.concr_values.json.~undo-tree~.zst
pyconcr/data/BrysbaertEtAl2014a/__init__.py
pyconcr/data/BrysbaertEtAl2014a/concr.json
pyconcr/data/BrysbaertEtAl2014a/concr_values.json
pyconcr/data/emacs-logo/emacs-128x128.png
pyconcr/data/emacs-logo/emacs.svg
pyconcr/factories/__init__.py
pyconcr/factories/get_doc_concreteness.py
pyconcr/tests/__init__.py
pyconcr/tests/test_pyconcr.py
pyconcr-0.0.1.dist-info/AUTHORS.rst
pyconcr-0.0.1.dist-info/LICENSE
pyconcr-0.0.1.dist-info/METADATA
pyconcr-0.0.1.dist-info/WHEEL
pyconcr-0.0.1.dist-info/entry_points.txt
pyconcr-0.0.1.dist-info/top_level.txt
pyconcr-0.0.1.dist-info/RECORD
